factofiction_analyzer/__init__.py
factofiction_analyzer/main.py
factofiction_analyzer/prompts.py
factofiction_analyzer-2025.12.21084430.dist-info/METADATA
factofiction_analyzer-2025.12.21084430.dist-info/WHEEL
factofiction_analyzer-2025.12.21084430.dist-info/top_level.txt
factofiction_analyzer-2025.12.21084430.dist-info/RECORD
