Metadata-Version: 2.4
Name: factofiction-analyzer
Version: 2025.12.21084430
Summary: A new package designed to help users distinguish between factual information and imaginative interpretations. This tool takes user-provided text as input and uses advanced language models to analyze a
Author-email: factofiction-analyzer <hi@eugene.plus>
License: MIT
Project-URL: Homepage, https://github.com/chigwell/factofiction-analyzer
Requires-Python: >=3.9
Requires-Dist: langchain-llm7>=0.0.0
Requires-Dist: llmatch-messages>=0.0.0
Requires-Dist: langchain-core>=0.3.0
